easy_recommender/__init__.py
easy_recommender/recommender.py
easy_recommender-0.1.3.dist-info/METADATA
easy_recommender-0.1.3.dist-info/WHEEL
easy_recommender-0.1.3.dist-info/RECORD
