Metadata-Version: 2.3
Name: easy-recommender
Version: 0.1.3
Summary: A simple recommendation system using LightFM
License: MIT
Keywords: recommendation,machine learning,collaborative filtering
Author: Your Name
Author-email: your.email@example.com
Requires-Python: >=3.11
Classifier: Development Status :: 3 - Alpha
Classifier: Intended Audience :: Developers
Classifier: License :: OSI Approved :: MIT License
Classifier: Programming Language :: Python :: 3
Classifier: Programming Language :: Python :: 3.11
Classifier: Programming Language :: Python :: 3.12
Classifier: Topic :: Scientific/Engineering :: Artificial Intelligence
Provides-Extra: dev
Requires-Dist: ipykernel (>=6.0.0) ; extra == "dev"
Requires-Dist: jupyter (>=1.0.0) ; extra == "dev"
Requires-Dist: jupyterlab (>=4.0.0) ; extra == "dev"
Requires-Dist: lightfm (>=1.17)
Requires-Dist: numpy (>=1.24.0)
Requires-Dist: pandas (>=2.0.0)
Requires-Dist: pytest (>=7.0.0) ; extra == "dev"
Requires-Dist: scikit-learn (>=1.3.0)
Project-URL: Homepage, https://github.com/t-kabaya/easy-recommender
Project-URL: Repository, https://github.com/t-kabaya/easy-recommender
